swtoolkit/__init__.py
swtoolkit/api/__init__.py
swtoolkit/api/assemblydoc.py
swtoolkit/api/com.py
swtoolkit/api/component.py
swtoolkit/api/custompropertymanager.py
swtoolkit/api/doc.py
swtoolkit/api/drawingdoc.py
swtoolkit/api/enums/__init__.py
swtoolkit/api/enums/enum_errors.py
swtoolkit/api/enums/enum_options.py
swtoolkit/api/enums/enum_results.py
swtoolkit/api/enums/enum_states.py
swtoolkit/api/enums/enum_types.py
swtoolkit/api/enums/enum_warnings.py
swtoolkit/api/errors/__init__.py
swtoolkit/api/feature.py
swtoolkit/api/featuremanager.py
swtoolkit/api/interfaces/__init__.py
swtoolkit/api/interfaces/iassemblydoc.py
swtoolkit/api/interfaces/icomponent.py
swtoolkit/api/interfaces/icustompropertymanager.py
swtoolkit/api/interfaces/idrawingdoc.py
swtoolkit/api/interfaces/ifeature.py
swtoolkit/api/interfaces/ifeaturemanager.py
swtoolkit/api/interfaces/imodeldoc.py
swtoolkit/api/interfaces/imodeldocextension.py
swtoolkit/api/interfaces/ipartdoc.py
swtoolkit/api/interfaces/isldworks.py
swtoolkit/api/modeldoc.py
swtoolkit/api/modeldocextension.py
swtoolkit/api/partdoc.py
swtoolkit/api/solidworks.py
swtoolkit/api/utils/__init__.py
swtoolkit/swtoolkit.py
swtoolkit/utils/__init__.py
swtoolkit-0.1.1.dist-info/LICENSE
swtoolkit-0.1.1.dist-info/WHEEL
swtoolkit-0.1.1.dist-info/METADATA
swtoolkit-0.1.1.dist-info/RECORD
