Metadata-Version: 2.1
Name: swtoolkit
Version: 0.1.1
Summary: A SolidWorks Toolkit for Python
Home-page: https://github.com/Glutenberg/swtoolkit.git
License: MIT
Author: Glutenberg
Author-email: josh@colescanada.com
Requires-Python: >=3.9,<4.0
Classifier: License :: OSI Approved :: MIT License
Classifier: Programming Language :: Python :: 3
Classifier: Programming Language :: Python :: 3.9
Requires-Dist: psutil (>=5.8.0,<6.0.0)
Requires-Dist: pywin32 (>=300,<301)
Project-URL: Repository, https://github.com/Glutenberg/swtoolkit.git
